setup.py
tock_loader.egg-info/PKG-INFO
tock_loader.egg-info/SOURCES.txt
tock_loader.egg-info/dependency_links.txt
tock_loader.egg-info/entry_points.txt
tock_loader.egg-info/requires.txt
tock_loader.egg-info/top_level.txt
tockloader/__init__.py
tockloader/main.py