Metadata-Version: 1.0
Name: tock-loader
Version: 0.1.0
Summary: TockOS Support Tool
Home-page: https://github.com/helena-project/tock-loader
Author: Tock Project Developers
Author-email: tock-dev@googlegroups.com
License: UNKNOWN
Platform: UNKNOWN
